edcapi/API.py
edcapi/__init__.py
edcapi/_version.py
edcapi-0.0.5.data/scripts/edc-downloader
edcapi-0.0.5.data/scripts/edc-uploader
edcapi-0.0.5.dist-info/METADATA
edcapi-0.0.5.dist-info/WHEEL
edcapi-0.0.5.dist-info/top_level.txt
edcapi-0.0.5.dist-info/RECORD
