Metadata-Version: 2.4
Name: edcapi
Version: 0.0.5
Summary: Eurolas Data Center API (EDC, https://edc.dgfi.tum.de)
Author: Christian Schwatke
Author-email: christian.schwatke@tum.de
License: MIT
Project-URL: EDC Homepage, https://edc.dgfi.tum.de/
Project-URL: Documentation, https://edc-api.readthedocs.io/
Project-URL: Source Code, https://gitlab.lrz.de/edc/python3-edcapi/
Classifier: Programming Language :: Python :: 3
Classifier: Operating System :: OS Independent
Requires-Python: >=3.8
Dynamic: author
Dynamic: author-email
Dynamic: classifier
Dynamic: description
Dynamic: description-content-type
Dynamic: license
Dynamic: project-url
Dynamic: requires-python
Dynamic: summary
